[{"unMeta":{"author":{"t":"MetaList","c":[{"t":"MetaInlines","c":[{"t":"Link","c":[["",[],[]],[{"t":"Str","c":"Sébastien"},{"t":"Space","c":[]},{"t":"Str","c":"Boisgérault"}],["mailto:Sebastien.Boisgerault@mines-paristech.fr",""]]},{"t":"Str","c":","},{"t":"Space","c":[]},{"t":"Str","c":"MINES"},{"t":"Space","c":[]},{"t":"Str","c":"ParisTech"}]}]},"title":{"t":"MetaInlines","c":[{"t":"Str","c":"Evolution"},{"t":"Space","c":[]},{"t":"Str","c":"of"},{"t":"Space","c":[]},{"t":"Str","c":"the"},{"t":"Space","c":[]},{"t":"Str","c":"Document"},{"t":"Space","c":[]},{"t":"Str","c":"Model"}]},"license":{"t":"MetaInlines","c":[{"t":"Link","c":[["",[],[]],[{"t":"Str","c":"CC"},{"t":"Space","c":[]},{"t":"Str","c":"BY-NC-SA"},{"t":"Space","c":[]},{"t":"Str","c":"4.0"}],["https://creativecommons.org/licenses/by-nc-sa/4.0",""]]}]}}},[{"t":"Header","c":[1,["introduction",[],[]],[{"t":"Str","c":"Introduction"}]]},{"t":"Para","c":[{"t":"Code","c":[["",[],[]],"Text.Pandoc.Definition"]},{"t":"Space","c":[]},{"t":"Str","c":"is"},{"t":"Space","c":[]},{"t":"Str","c":"the"},{"t":"Space","c":[]},{"t":"Str","c":"module"},{"t":"Space","c":[]},{"t":"Str","c":"of"},{"t":"Space","c":[]},{"t":"Str","c":"the"},{"t":"Space","c":[]},{"t":"Link","c":[["",[],[]],[{"t":"Str","c":"pandoc-types"}],["https://hackage.haskell.org/package/pandoc-types",""]]},{"t":"Space","c":[]},{"t":"Str","c":"Haskell"},{"t":"Space","c":[]},{"t":"Str","c":"package"},{"t":"SoftBreak","c":[]},{"t":"Str","c":"that"},{"t":"Space","c":[]},{"t":"Str","c":"contains"},{"t":"Space","c":[]},{"t":"Str","c":"the"},{"t":"Space","c":[]},{"t":"Str","c":"definitions"},{"t":"Space","c":[]},{"t":"Str","c":"for"},{"t":"Space","c":[]},{"t":"Str","c":"the"},{"t":"Space","c":[]},{"t":"Str","c":"Pandoc"},{"t":"Space","c":[]},{"t":"Str","c":"data"},{"t":"Space","c":[]},{"t":"Str","c":"structure"},{"t":"SoftBreak","c":[]},{"t":"Str","c":"used"},{"t":"Space","c":[]},{"t":"Str","c":"by"},{"t":"Space","c":[]},{"t":"Str","c":"pandoc"},{"t":"Space","c":[]},{"t":"Str","c":"to"},{"t":"Space","c":[]},{"t":"Str","c":"represent"},{"t":"Space","c":[]},{"t":"Str","c":"structured"},{"t":"Space","c":[]},{"t":"Str","c":"documents."}]},{"t":"Para","c":[{"t":"Str","c":"Actually,"},{"t":"Space","c":[]},{"t":"Str","c":"there"},{"t":"Space","c":[]},{"t":"Str","c":"is"},{"t":"Space","c":[]},{"t":"Str","c":"not"},{"t":"Space","c":[]},{"t":"Str","c":"a"},{"t":"Space","c":[]},{"t":"Str","c":"single"},{"t":"Space","c":[]},{"t":"Str","c":"model"},{"t":"Space","c":[]},{"t":"Str","c":"of"},{"t":"Space","c":[]},{"t":"Str","c":"document,"},{"t":"SoftBreak","c":[]},{"t":"Str","c":"but"},{"t":"Space","c":[]},{"t":"Str","c":"a"},{"t":"Space","c":[]},{"t":"Str","c":"collection"},{"t":"Space","c":[]},{"t":"Str","c":"of"},{"t":"Space","c":[]},{"t":"Str","c":"models"},{"t":"Space","c":[]},{"t":"Str","c":"since"},{"t":"Space","c":[]},{"t":"Str","c":"the"},{"t":"Space","c":[]},{"t":"Str","c":"original"},{"t":"Space","c":[]},{"t":"Str","c":"design"},{"t":"SoftBreak","c":[]},{"t":"Str","c":"has"},{"t":"Space","c":[]},{"t":"Str","c":"evolved"},{"t":"Space","c":[]},{"t":"Str","c":"over"},{"t":"Space","c":[]},{"t":"Str","c":"time."},{"t":"SoftBreak","c":[]},{"t":"Str","c":"Unless"},{"t":"Space","c":[]},{"t":"Str","c":"you"},{"t":"Space","c":[]},{"t":"Str","c":"deliberately"},{"t":"Space","c":[]},{"t":"Str","c":"use"},{"t":"Space","c":[]},{"t":"Str","c":"a"},{"t":"Space","c":[]},{"t":"Str","c":"fixed"},{"t":"Space","c":[]},{"t":"Str","c":"version"},{"t":"Space","c":[]},{"t":"Str","c":"of"},{"t":"Space","c":[]},{"t":"Str","c":"pandoc"},{"t":"SoftBreak","c":[]},{"t":"Str","c":"–"},{"t":"Space","c":[]},{"t":"Str","c":"and"},{"t":"Space","c":[]},{"t":"Str","c":"therefore"},{"t":"Space","c":[]},{"t":"Str","c":"a"},{"t":"Space","c":[]},{"t":"Str","c":"unique"},{"t":"Space","c":[]},{"t":"Str","c":"document"},{"t":"Space","c":[]},{"t":"Str","c":"model"},{"t":"Space","c":[]},{"t":"Str","c":"–"},{"t":"SoftBreak","c":[]},{"t":"Str","c":"you"},{"t":"Space","c":[]},{"t":"Str","c":"may"},{"t":"Space","c":[]},{"t":"Str","c":"at"},{"t":"Space","c":[]},{"t":"Str","c":"some"},{"t":"Space","c":[]},{"t":"Str","c":"point"},{"t":"Space","c":[]},{"t":"Str","c":"need"},{"t":"Space","c":[]},{"t":"Str","c":"to"},{"t":"Space","c":[]},{"t":"Str","c":"manage"},{"t":"Space","c":[]},{"t":"Str","c":"several"},{"t":"SoftBreak","c":[]},{"t":"Str","c":"models"},{"t":"Space","c":[]},{"t":"Str","c":"of"},{"t":"Space","c":[]},{"t":"Str","c":"documents."}]},{"t":"Para","c":[{"t":"Str","c":"To"},{"t":"Space","c":[]},{"t":"Str","c":"ease"},{"t":"Space","c":[]},{"t":"Str","c":"this"},{"t":"Space","c":[]},{"t":"Str","c":"work,"},{"t":"Space","c":[]},{"t":"Str","c":"we"},{"t":"Space","c":[]},{"t":"Str","c":"describe"},{"t":"Space","c":[]},{"t":"Str","c":"here"},{"t":"Space","c":[]},{"t":"Str","c":"the"},{"t":"Space","c":[]},{"t":"Str","c":"evolution"},{"t":"Space","c":[]},{"t":"Str","c":"of"},{"t":"Space","c":[]},{"t":"Str","c":"this"},{"t":"Space","c":[]},{"t":"Str","c":"model,"},{"t":"SoftBreak","c":[]},{"t":"Str","c":"from"},{"t":"Space","c":[]},{"t":"Str","c":"the"},{"t":"Space","c":[]},{"t":"Str","c":"creation"},{"t":"Space","c":[]},{"t":"Str","c":"of"},{"t":"Space","c":[]},{"t":"Str","c":"pandoc-types"},{"t":"Space","c":[]},{"t":"Str","c":"to"},{"t":"Space","c":[]},{"t":"Str","c":"the"},{"t":"Space","c":[]},{"t":"Str","c":"present"},{"t":"Space","c":[]},{"t":"Str","c":"day."}]},{"t":"Header","c":[1,["evolutions",[],[]],[{"t":"Str","c":"Evolutions"}]]},{"t":"Header","c":[2,["version-1.7",[],[]],[{"t":"Str","c":"Version"},{"t":"Space","c":[]},{"t":"Str","c":"1.7"}]]},{"t":"Para","c":[{"t":"Str","c":"The"},{"t":"Space","c":[]},{"t":"Str","c":"original"},{"t":"Space","c":[]},{"t":"Str","c":"model,"},{"t":"Space","c":[]},{"t":"Str","c":"included"},{"t":"Space","c":[]},{"t":"Str","c":"below"},{"t":"Space","c":[]},{"t":"Str","c":"for"},{"t":"Space","c":[]},{"t":"Str","c":"the"},{"t":"Space","c":[]},{"t":"Str","c":"sake"},{"t":"Space","c":[]},{"t":"Str","c":"of"},{"t":"Space","c":[]},{"t":"Str","c":"completeness:"},{"t":"SoftBreak","c":[]},{"t":"Str","c":"66"},{"t":"Space","c":[]},{"t":"Str","c":"lines"},{"t":"Space","c":[]},{"t":"Str","c":"only,"},{"t":"Space","c":[]},{"t":"Str","c":"that"},{"t":"Space","c":[]},{"t":"Str","c":"describe"},{"t":"Space","c":[]},{"t":"Str","c":"the"},{"t":"Space","c":[]},{"t":"Str","c":"structure"},{"t":"Space","c":[]},{"t":"Str","c":"of"},{"t":"Space","c":[]},{"t":"Str","c":"any"},{"t":"Space","c":[]},{"t":"Str","c":"pandoc"},{"t":"Space","c":[]},{"t":"Str","c":"document."}]},{"t":"CodeBlock","c":[["",[],[]],"data Pandoc = Pandoc Meta [Block]\ndata Meta\n  = Meta {docTitle :: [Inline],\n          docAuthors :: [[Inline]],\n          docDate :: [Inline]}\ndata Alignment\n  = AlignLeft | AlignRight | AlignCenter | AlignDefault\ntype ListAttributes = (Int, ListNumberStyle, ListNumberDelim)\ndata ListNumberStyle\n  = DefaultStyle\n  | Example\n  | Decimal\n  | LowerRoman\n  | UpperRoman\n  | LowerAlpha\n  | UpperAlpha\ndata ListNumberDelim = DefaultDelim | Period | OneParen | TwoParens\ntype Attr = (String, [String], [(String, String)])\ntype TableCell = [Block]\ndata Block\n  = Plain [Inline]\n  | Para [Inline]\n  | CodeBlock Attr String\n  | RawHtml String\n  | BlockQuote [Block]\n  | OrderedList ListAttributes [[Block]]\n  | BulletList [[Block]]\n  | DefinitionList [([Inline], [[Block]])]\n  | Header Int [Inline]\n  | HorizontalRule\n  | Table [Inline] [Alignment] [Double] [TableCell] [[TableCell]]\n  | Null\ndata QuoteType = SingleQuote | DoubleQuote\ntype Target = (String, String)\ndata MathType = DisplayMath | InlineMath\ndata Inline\n  = Str String\n  | Emph [Inline]\n  | Strong [Inline]\n  | Strikeout [Inline]\n  | Superscript [Inline]\n  | Subscript [Inline]\n  | SmallCaps [Inline]\n  | Quoted QuoteType [Inline]\n  | Cite [Citation] [Inline]\n  | Code String\n  | Space\n  | EmDash\n  | EnDash\n  | Apostrophe\n  | Ellipses\n  | LineBreak\n  | Math MathType String\n  | TeX String\n  | HtmlInline String\n  | Link [Inline] Target\n  | Image [Inline] Target\n  | Note [Block]\ndata Citation\n  = Citation {citationId :: String,\n              citationPrefix :: [Inline],\n              citationSuffix :: [Inline],\n              citationMode :: CitationMode,\n              citationNoteNum :: Int,\n              citationHash :: Int}\ndata CitationMode = AuthorInText | SuppressAuthor | NormalCitation"]},{"t":"Header","c":[2,["version-1.8",[],[]],[{"t":"Str","c":"Version"},{"t":"Space","c":[]},{"t":"Str","c":"1.8"}]]},{"t":"Header","c":[3,["inline-code-gets-attributes",[],[]],[{"t":"Str","c":"Inline"},{"t":"Space","c":[]},{"t":"Str","c":"code"},{"t":"Space","c":[]},{"t":"Str","c":"gets"},{"t":"Space","c":[]},{"t":"Str","c":"attributes"}]]},{"t":"Para","c":[{"t":"Str","c":"The"},{"t":"Space","c":[]},{"t":"Str","c":"code"},{"t":"Space","c":[]},{"t":"Str","c":"block"},{"t":"Space","c":[]},{"t":"Str","c":"element"},{"t":"Space","c":[]},{"t":"Str","c":"of"},{"t":"Space","c":[]},{"t":"Str","c":"the"},{"t":"Space","c":[]},{"t":"Str","c":"1.7"},{"t":"Space","c":[]},{"t":"Str","c":"document"},{"t":"Space","c":[]},{"t":"Str","c":"model"},{"t":"Space","c":[]},{"t":"Str","c":"has"},{"t":"Space","c":[]},{"t":"Str","c":"an"},{"t":"Space","c":[]},{"t":"Str","c":"attributes"},{"t":"SoftBreak","c":[]},{"t":"Str","c":"("},{"t":"Code","c":[["",[],[]],"Attr"]},{"t":"Str","c":")"},{"t":"Space","c":[]},{"t":"Str","c":"field."},{"t":"SoftBreak","c":[]},{"t":"Str","c":"For"},{"t":"Space","c":[]},{"t":"Str","c":"example,"},{"t":"Space","c":[]},{"t":"Str","c":"a"},{"t":"Space","c":[]},{"t":"Str","c":"code"},{"t":"Space","c":[]},{"t":"Str","c":"block"},{"t":"Space","c":[]},{"t":"Str","c":"described"},{"t":"Space","c":[]},{"t":"Str","c":"by"}]},{"t":"CodeBlock","c":[["",[],[]],"~~~~ {#mycode .haskell .numberLines startFrom=\"100\"}\nqsort []     = []\nqsort (x:xs) = qsort (filter (< x) xs) ++ [x] ++\n               qsort (filter (>= x) xs)\n~~~~~~~~~~~~~~~~~~~~~~~~~~~~~~~~~~~~~~~~~~~~~~~~~"]},{"t":"Para","c":[{"t":"Str","c":"has"},{"t":"Space","c":[]},{"t":"Str","c":"the"},{"t":"Space","c":[]},{"t":"Str","c":"attributes"},{"t":"Space","c":[]},{"t":"Str","c":"field"}]},{"t":"CodeBlock","c":[["",[],[]],"[[\"mycode\",[\"haskell\",\"numberLines\"],[[\"startFrom\",\"100\"]]]"]},{"t":"Para","c":[{"t":"Str","c":"This"},{"t":"Space","c":[]},{"t":"Str","c":"triple"},{"t":"Space","c":[]},{"t":"Str","c":"should"},{"t":"Space","c":[]},{"t":"Str","c":"be"},{"t":"Space","c":[]},{"t":"Str","c":"interpreted"},{"t":"Space","c":[]},{"t":"Str","c":"as"},{"t":"Space","c":[]},{"t":"Str","c":"id,"},{"t":"Space","c":[]},{"t":"Str","c":"classes"},{"t":"Space","c":[]},{"t":"Str","c":"and"},{"t":"Space","c":[]},{"t":"Str","c":"key-value"},{"t":"Space","c":[]},{"t":"Str","c":"pairs,"},{"t":"SoftBreak","c":[]},{"t":"Str","c":"something"},{"t":"Space","c":[]},{"t":"Str","c":"very"},{"t":"Space","c":[]},{"t":"Str","c":"similar"},{"t":"Space","c":[]},{"t":"Str","c":"to"},{"t":"Space","c":[]},{"t":"Str","c":"the"},{"t":"Space","c":[]},{"t":"Str","c":"model"},{"t":"Space","c":[]},{"t":"Str","c":"of"},{"t":"Space","c":[]},{"t":"Str","c":"HTML"},{"t":"Space","c":[]},{"t":"Str","c":"elements."}]},{"t":"Para","c":[{"t":"Str","c":"In"},{"t":"Space","c":[]},{"t":"Str","c":"the"},{"t":"Space","c":[]},{"t":"Str","c":"1.7"},{"t":"Space","c":[]},{"t":"Str","c":"model,"},{"t":"Space","c":[]},{"t":"Str","c":"however,"},{"t":"Space","c":[]},{"t":"Str","c":"inline"},{"t":"Space","c":[]},{"t":"Str","c":"code"},{"t":"Space","c":[]},{"t":"Str","c":"lack"},{"t":"Space","c":[]},{"t":"Str","c":"attributes;"},{"t":"SoftBreak","c":[]},{"t":"Str","c":"in"},{"t":"Space","c":[]},{"t":"Str","c":"the"},{"t":"Space","c":[]},{"t":"Str","c":"1.8"},{"t":"Space","c":[]},{"t":"Str","c":"version,"},{"t":"Space","c":[]},{"t":"Str","c":"they"},{"t":"Space","c":[]},{"t":"Str","c":"get"},{"t":"Space","c":[]},{"t":"Str","c":"this"},{"t":"Space","c":[]},{"t":"Str","c":"field"},{"t":"Space","c":[]},{"t":"Str","c":"too:"}]},{"t":"CodeBlock","c":[["",[],[]],"data Inline\n  = ...\n  | Code Attr String\n  | ..."]},{"t":"Para","c":[{"t":"Str","c":"For"},{"t":"Space","c":[]},{"t":"Str","c":"example,"},{"t":"Space","c":[]},{"t":"Str","c":"the"},{"t":"Space","c":[]},{"t":"Str","c":"markdown"},{"t":"Space","c":[]},{"t":"Str","c":"text"}]},{"t":"CodeBlock","c":[["",[],[]],"`<$>`{.haskell}"]},{"t":"Para","c":[{"t":"Str","c":"attaches"},{"t":"Space","c":[]},{"t":"Str","c":"the"},{"t":"Space","c":[]},{"t":"Str","c":"class"},{"t":"Space","c":[]},{"t":"Code","c":[["",[],[]],"haskell"]},{"t":"Space","c":[]},{"t":"Str","c":"to"},{"t":"Space","c":[]},{"t":"Str","c":"the"},{"t":"Space","c":[]},{"t":"Str","c":"inline"},{"t":"Space","c":[]},{"t":"Str","c":"code"},{"t":"Space","c":[]},{"t":"Code","c":[["",[],[]],"<$>"]},{"t":"Str","c":"."},{"t":"SoftBreak","c":[]},{"t":"Str","c":"A"},{"t":"Space","c":[]},{"t":"Code","c":[["",[],[]],"nullAttr"]},{"t":"Space","c":[]},{"t":"Str","c":"constant"},{"t":"Space","c":[]},{"t":"Str","c":"is"},{"t":"Space","c":[]},{"t":"Str","c":"also"},{"t":"Space","c":[]},{"t":"Str","c":"introduced"},{"t":"Space","c":[]},{"t":"Str","c":"to"},{"t":"Space","c":[]},{"t":"Str","c":"denote"},{"t":"Space","c":[]},{"t":"Str","c":"the"},{"t":"Space","c":[]},{"t":"Str","c":"default"},{"t":"SoftBreak","c":[]},{"t":"Str","c":"value"},{"t":"Space","c":[]},{"t":"Str","c":"of"},{"t":"Space","c":[]},{"t":"Str","c":"the"},{"t":"Space","c":[]},{"t":"Str","c":"attributes"},{"t":"Space","c":[]},{"t":"Str","c":"field"}]},{"t":"CodeBlock","c":[["",[],[]],"nullAttr :: Attr"]},{"t":"Header","c":[3,["raw-elements",[],[]],[{"t":"Str","c":"Raw"},{"t":"Space","c":[]},{"t":"Str","c":"elements"}]]},{"t":"Para","c":[{"t":"Str","c":"In"},{"t":"Space","c":[]},{"t":"Str","c":"the"},{"t":"Space","c":[]},{"t":"Str","c":"1.7"},{"t":"Space","c":[]},{"t":"Str","c":"model,"},{"t":"Space","c":[]},{"t":"Str","c":"HTML"},{"t":"Space","c":[]},{"t":"Str","c":"fragments"},{"t":"Space","c":[]},{"t":"Str","c":"could"},{"t":"Space","c":[]},{"t":"Str","c":"be"},{"t":"Space","c":[]},{"t":"Str","c":"inserted"},{"t":"Space","c":[]},{"t":"Str","c":"in"},{"t":"Space","c":[]},{"t":"Str","c":"documents"},{"t":"SoftBreak","c":[]},{"t":"Str","c":"as"},{"t":"Space","c":[]},{"t":"Code","c":[["",[],[]],"RawHtml"]},{"t":"Space","c":[]},{"t":"Str","c":"blocks"},{"t":"Space","c":[]},{"t":"Str","c":"or"},{"t":"Space","c":[]},{"t":"Code","c":[["",[],[]],"HtmlInline"]},{"t":"Space","c":[]},{"t":"Str","c":"inlines;"},{"t":"Space","c":[]},{"t":"Str","c":"TeX"},{"t":"Space","c":[]},{"t":"Str","c":"fragments"},{"t":"Space","c":[]},{"t":"Str","c":"could"},{"t":"SoftBreak","c":[]},{"t":"Str","c":"only"},{"t":"Space","c":[]},{"t":"Str","c":"be"},{"t":"Space","c":[]},{"t":"Str","c":"inline,"},{"t":"Space","c":[]},{"t":"Str","c":"with"},{"t":"Space","c":[]},{"t":"Str","c":"the"},{"t":"Space","c":[]},{"t":"Code","c":[["",[],[]],"TeX"]},{"t":"Space","c":[]},{"t":"Str","c":"type."}]},{"t":"Para","c":[{"t":"Str","c":"In"},{"t":"Space","c":[]},{"t":"Str","c":"the"},{"t":"Space","c":[]},{"t":"Str","c":"1.8"},{"t":"Space","c":[]},{"t":"Str","c":"model,"},{"t":"Space","c":[]},{"t":"Str","c":"these"},{"t":"Space","c":[]},{"t":"Str","c":"constructs"},{"t":"Space","c":[]},{"t":"Str","c":"are"},{"t":"Space","c":[]},{"t":"Str","c":"generalized"},{"t":"Space","c":[]},{"t":"Str","c":"and"},{"t":"Space","c":[]},{"t":"Str","c":"merged:"},{"t":"SoftBreak","c":[]},{"t":"Str","c":"native"},{"t":"Space","c":[]},{"t":"Str","c":"(HTML"},{"t":"Space","c":[]},{"t":"Str","c":"or"},{"t":"Space","c":[]},{"t":"Str","c":"TeX)"},{"t":"Space","c":[]},{"t":"Str","c":"elements"},{"t":"Space","c":[]},{"t":"Str","c":"are"},{"t":"Space","c":[]},{"t":"Str","c":"now"},{"t":"Space","c":[]},{"t":"Str","c":"described"},{"t":"Space","c":[]},{"t":"Str","c":"either"},{"t":"Space","c":[]},{"t":"Str","c":"as"},{"t":"Space","c":[]},{"t":"Str","c":"raw"},{"t":"SoftBreak","c":[]},{"t":"Str","c":"blocks"},{"t":"Space","c":[]},{"t":"Str","c":"or"},{"t":"Space","c":[]},{"t":"Str","c":"raw"},{"t":"Space","c":[]},{"t":"Str","c":"inlines:"}]},{"t":"CodeBlock","c":[["",[],[]],"type Format = String\ndata Block\n  = ...\n  | RawBlock Format String\n  | ...\ndata Inline\n  = ...\n  | RawInline Format String\n  | ..."]},{"t":"Para","c":[{"t":"Str","c":"Concretely,"},{"t":"Space","c":[]},{"t":"Str","c":"the"},{"t":"Space","c":[]},{"t":"Str","c":"format"},{"t":"Space","c":[]},{"t":"Str","c":"is"},{"t":"Space","c":[]},{"t":"Str","c":"either"},{"t":"Space","c":[]},{"t":"Quoted","c":[{"t":"DoubleQuote","c":[]},[{"t":"Str","c":"tex"}]]},{"t":"Space","c":[]},{"t":"Str","c":"or"},{"t":"Space","c":[]},{"t":"Quoted","c":[{"t":"DoubleQuote","c":[]},[{"t":"Str","c":"html"}]]},{"t":"SoftBreak","c":[]},{"t":"Str","c":"but"},{"t":"Space","c":[]},{"t":"Str","c":"this"},{"t":"Space","c":[]},{"t":"Str","c":"is"},{"t":"Space","c":[]},{"t":"Str","c":"a"},{"t":"Space","c":[]},{"t":"Str","c":"not"},{"t":"Space","c":[]},{"t":"Str","c":"a"},{"t":"Space","c":[]},{"t":"Str","c":"hard"},{"t":"Space","c":[]},{"t":"Str","c":"constraint"},{"t":"Space","c":[]},{"t":"Str","c":"of"},{"t":"Space","c":[]},{"t":"Str","c":"the"},{"t":"Space","c":[]},{"t":"Str","c":"document"},{"t":"Space","c":[]},{"t":"Str","c":"model."}]},{"t":"Header","c":[2,["version-1.9.0.1",[],[]],[{"t":"Str","c":"Version"},{"t":"Space","c":[]},{"t":"Str","c":"1.9(.0.1)"}]]},{"t":"Para","c":[{"t":"Str","c":"(there"},{"t":"Space","c":[]},{"t":"Str","c":"is"},{"t":"Space","c":[]},{"t":"Str","c":"no"},{"t":"Space","c":[]},{"t":"Str","c":"version"},{"t":"Space","c":[]},{"t":"Str","c":"1.9"},{"t":"Space","c":[]},{"t":"Str","c":"released,"},{"t":"Space","c":[]},{"t":"Str","c":"only"},{"t":"Space","c":[]},{"t":"Str","c":"1.9.0.1,"},{"t":"Space","c":[]},{"t":"Str","c":"1.9.0.2"},{"t":"Space","c":[]},{"t":"Str","c":"and"},{"t":"Space","c":[]},{"t":"Str","c":"1.9.1)"}]},{"t":"Header","c":[3,["new-representation-for-em-dash-en-dash-apostrophe-and-ellipses",[],[]],[{"t":"Str","c":"New"},{"t":"Space","c":[]},{"t":"Str","c":"representation"},{"t":"Space","c":[]},{"t":"Str","c":"for"},{"t":"Space","c":[]},{"t":"Str","c":"em-dash,"},{"t":"Space","c":[]},{"t":"Str","c":"en-dash,"},{"t":"Space","c":[]},{"t":"Str","c":"apostrophe"},{"t":"Space","c":[]},{"t":"Str","c":"and"},{"t":"Space","c":[]},{"t":"Str","c":"ellipses"}]]},{"t":"Para","c":[{"t":"Code","c":[["",[],[]],"EmDash"]},{"t":"Str","c":","},{"t":"Space","c":[]},{"t":"Code","c":[["",[],[]],"EnDash"]},{"t":"Str","c":","},{"t":"Space","c":[]},{"t":"Code","c":[["",[],[]],"Apostrophe"]},{"t":"Space","c":[]},{"t":"Str","c":"and"},{"t":"Space","c":[]},{"t":"Code","c":[["",[],[]],"Ellipses"]},{"t":"Space","c":[]},{"t":"Str","c":"disappear"},{"t":"SoftBreak","c":[]},{"t":"Str","c":"from"},{"t":"Space","c":[]},{"t":"Str","c":"the"},{"t":"Space","c":[]},{"t":"Code","c":[["",[],[]],"Inline"]},{"t":"Space","c":[]},{"t":"Str","c":"type."},{"t":"Space","c":[]},{"t":"Str","c":"You"},{"t":"Space","c":[]},{"t":"Str","c":"can"},{"t":"Space","c":[]},{"t":"Str","c":"still"},{"t":"Space","c":[]},{"t":"Str","c":"use"},{"t":"Space","c":[]},{"t":"Str","c":"the"},{"t":"Space","c":[]},{"t":"Str","c":"corresponding"},{"t":"SoftBreak","c":[]},{"t":"Str","c":"constructs"},{"t":"Space","c":[]},{"t":"Str","c":"in"},{"t":"Space","c":[]},{"t":"Str","c":"you"},{"t":"Space","c":[]},{"t":"Str","c":"markdown"},{"t":"Space","c":[]},{"t":"Str","c":"text,"},{"t":"Space","c":[]},{"t":"Str","c":"but"},{"t":"Space","c":[]},{"t":"Str","c":"they"},{"t":"Space","c":[]},{"t":"Str","c":"will"},{"t":"Space","c":[]},{"t":"Str","c":"be"},{"t":"Space","c":[]},{"t":"Str","c":"described"},{"t":"SoftBreak","c":[]},{"t":"Str","c":"as"},{"t":"Space","c":[]},{"t":"Str","c":"regular"},{"t":"Space","c":[]},{"t":"Str","c":"string"},{"t":"Space","c":[]},{"t":"Str","c":"("},{"t":"Code","c":[["",[],[]],"Str"]},{"t":"Str","c":")"},{"t":"Space","c":[]},{"t":"Str","c":"instances,"},{"t":"Space","c":[]},{"t":"Str","c":"which"},{"t":"Space","c":[]},{"t":"Str","c":"makes"},{"t":"Space","c":[]},{"t":"Str","c":"sense:"},{"t":"SoftBreak","c":[]},{"t":"Str","c":"since"},{"t":"Space","c":[]},{"t":"Str","c":"the"},{"t":"Space","c":[]},{"t":"Str","c":"unicode"},{"t":"Space","c":[]},{"t":"Str","c":"standard"},{"t":"Space","c":[]},{"t":"Str","c":"knows"},{"t":"Space","c":[]},{"t":"Str","c":"about"},{"t":"Space","c":[]},{"t":"Str","c":"them,"},{"t":"SoftBreak","c":[]},{"t":"Str","c":"it"},{"t":"Space","c":[]},{"t":"Str","c":"is"},{"t":"Space","c":[]},{"t":"Str","c":"pointless"},{"t":"Space","c":[]},{"t":"Str","c":"to"},{"t":"Space","c":[]},{"t":"Str","c":"have"},{"t":"Space","c":[]},{"t":"Str","c":"an"},{"t":"Space","c":[]},{"t":"Str","c":"extra"},{"t":"Space","c":[]},{"t":"Str","c":"construct."}]},{"t":"Header","c":[2,["version-1.12",[],[]],[{"t":"Str","c":"Version"},{"t":"Space","c":[]},{"t":"Str","c":"1.12"}]]},{"t":"Header","c":[3,["a-new-metadata-model",[],[]],[{"t":"Str","c":"A"},{"t":"Space","c":[]},{"t":"Str","c":"new"},{"t":"Space","c":[]},{"t":"Str","c":"metadata"},{"t":"Space","c":[]},{"t":"Str","c":"model"}]]},{"t":"Para","c":[{"t":"Str","c":"In"},{"t":"Space","c":[]},{"t":"Str","c":"the"},{"t":"Space","c":[]},{"t":"Str","c":"initial"},{"t":"Space","c":[]},{"t":"Str","c":"document"},{"t":"Space","c":[]},{"t":"Str","c":"model,"},{"t":"Space","c":[]},{"t":"Str","c":"the"},{"t":"Space","c":[]},{"t":"Str","c":"metadata"},{"t":"Space","c":[]},{"t":"Str","c":"of"},{"t":"Space","c":[]},{"t":"Str","c":"a"},{"t":"Space","c":[]},{"t":"Str","c":"document"},{"t":"SoftBreak","c":[]},{"t":"Str","c":"was"},{"t":"Space","c":[]},{"t":"Str","c":"made"},{"t":"Space","c":[]},{"t":"Str","c":"of"},{"t":"Space","c":[]},{"t":"Str","c":"three"},{"t":"Space","c":[]},{"t":"Str","c":"fixed"},{"t":"Space","c":[]},{"t":"Str","c":"attributes,"},{"t":"Space","c":[]},{"t":"Str","c":"specified"},{"t":"Space","c":[]},{"t":"Str","c":"in"},{"t":"Space","c":[]},{"t":"Str","c":"a"},{"t":"Space","c":[]},{"t":"Link","c":[["",[],[]],[{"t":"Str","c":"title"},{"t":"Space","c":[]},{"t":"Str","c":"block"}],["https://pandoc.org/MANUAL.html#extension-pandoc_title_block",""]]},{"t":"Str","c":":"},{"t":"SoftBreak","c":[]},{"t":"Str","c":"the"},{"t":"Space","c":[]},{"t":"Str","c":"document"},{"t":"Space","c":[]},{"t":"Str","c":"title,"},{"t":"Space","c":[]},{"t":"Str","c":"author"},{"t":"Space","c":[]},{"t":"Str","c":"list"},{"t":"Space","c":[]},{"t":"Str","c":"and"},{"t":"Space","c":[]},{"t":"Str","c":"date."}]},{"t":"CodeBlock","c":[["",[],[]],"data Meta\n  = Meta {docTitle :: [Inline],\n          docAuthors :: [[Inline]],\n          docDate :: [Inline]}"]},{"t":"Para","c":[{"t":"Str","c":"A"},{"t":"Space","c":[]},{"t":"Str","c":"typical"},{"t":"Space","c":[]},{"t":"Str","c":"markdown"},{"t":"Space","c":[]},{"t":"Str","c":"document"},{"t":"Space","c":[]},{"t":"Str","c":"would"},{"t":"Space","c":[]},{"t":"Str","c":"start"},{"t":"Space","c":[]},{"t":"Str","c":"with"},{"t":"SoftBreak","c":[]},{"t":"Str","c":"lines"},{"t":"Space","c":[]},{"t":"Str","c":"prefixed"},{"t":"Space","c":[]},{"t":"Str","c":"by"},{"t":"Space","c":[]},{"t":"Str","c":"percentages"},{"t":"Space","c":[]},{"t":"Str","c":"to"},{"t":"Space","c":[]},{"t":"Str","c":"specify"},{"t":"Space","c":[]},{"t":"Str","c":"these"},{"t":"Space","c":[]},{"t":"Str","c":"attributes,"},{"t":"SoftBreak","c":[]},{"t":"Str","c":"such"},{"t":"Space","c":[]},{"t":"Str","c":"as"}]},{"t":"CodeBlock","c":[["",[],[]]," % Document Title\n % Author 1; Author 2; Author 3\n % Date"]},{"t":"Para","c":[{"t":"Str","c":"Starting"},{"t":"Space","c":[]},{"t":"Str","c":"with"},{"t":"Space","c":[]},{"t":"Str","c":"1.12,"},{"t":"Space","c":[]},{"t":"Str","c":"pandoc"},{"t":"Space","c":[]},{"t":"Str","c":"support"},{"t":"Space","c":[]},{"t":"Str","c":"arbitrary"},{"t":"Space","c":[]},{"t":"Link","c":[["",[],[]],[{"t":"Str","c":"YAML"},{"t":"Space","c":[]},{"t":"Str","c":"metadata"},{"t":"Space","c":[]},{"t":"Str","c":"blocks"}],["https://pandoc.org/MANUAL.html#extension-yaml_metadata_block",""]]}]},{"t":"CodeBlock","c":[["",[],[]],"newtype Meta = Meta {unMeta :: Map String MetaValue}\ndata MetaValue\n  = MetaMap (Map String MetaValue)\n  | MetaList [MetaValue]\n  | MetaBool Bool\n  | MetaString String\n  | MetaInlines [Inline]\n  | MetaBlocks [Block]"]},{"t":"Para","c":[{"t":"Str","c":"Helper"},{"t":"Space","c":[]},{"t":"Str","c":"functions"},{"t":"Space","c":[]},{"t":"Str","c":"are"},{"t":"Space","c":[]},{"t":"Str","c":"created"},{"t":"Space","c":[]},{"t":"Str","c":"to"},{"t":"Space","c":[]},{"t":"Str","c":"help"},{"t":"Space","c":[]},{"t":"Str","c":"with"},{"t":"Space","c":[]},{"t":"Str","c":"the"},{"t":"Space","c":[]},{"t":"Str","c":"new"},{"t":"Space","c":[]},{"t":"Str","c":"structure,"},{"t":"SoftBreak","c":[]},{"t":"Str","c":"for"},{"t":"Space","c":[]},{"t":"Str","c":"example"},{"t":"Space","c":[]},{"t":"Str","c":"to"},{"t":"Space","c":[]},{"t":"Str","c":"get"},{"t":"Space","c":[]},{"t":"Str","c":"the"},{"t":"Space","c":[]},{"t":"Str","c":"title,"},{"t":"Space","c":[]},{"t":"Str","c":"authors"},{"t":"Space","c":[]},{"t":"Str","c":"and"},{"t":"Space","c":[]},{"t":"Str","c":"date."}]},{"t":"CodeBlock","c":[["",[],[]],"nullMeta :: Meta\nisNullMeta :: Meta -> Bool\nlookupMeta :: String -> Meta -> Maybe MetaValue\ndocTitle :: Meta -> [Inline]\ndocAuthors :: Meta -> [[Inline]]\ndocDate :: Meta -> [Inline]"]},{"t":"Header","c":[3,["introduction-of-span-and-div",[],[]],[{"t":"Str","c":"Introduction"},{"t":"Space","c":[]},{"t":"Str","c":"of"},{"t":"Space","c":[]},{"t":"Str","c":"span"},{"t":"Space","c":[]},{"t":"Str","c":"and"},{"t":"Space","c":[]},{"t":"Str","c":"div"}]]},{"t":"Para","c":[{"t":"Str","c":"The"},{"t":"Space","c":[]},{"t":"Str","c":"span"},{"t":"Space","c":[]},{"t":"Str","c":"and"},{"t":"Space","c":[]},{"t":"Str","c":"div"},{"t":"Space","c":[]},{"t":"Str","c":"constructs"},{"t":"Space","c":[]},{"t":"Str","c":"from"},{"t":"Space","c":[]},{"t":"Str","c":"HTML"},{"t":"Space","c":[]},{"t":"Str","c":"are"},{"t":"Space","c":[]},{"t":"Str","c":"incorporated"},{"t":"Space","c":[]},{"t":"Str","c":"to"},{"t":"Space","c":[]},{"t":"Str","c":"the"},{"t":"Space","c":[]},{"t":"Str","c":"document"},{"t":"SoftBreak","c":[]},{"t":"Str","c":"model,"},{"t":"Space","c":[]},{"t":"Str","c":"as"},{"t":"Space","c":[]},{"t":"Str","c":"inline"},{"t":"Space","c":[]},{"t":"Str","c":"and"},{"t":"Space","c":[]},{"t":"Str","c":"block"},{"t":"Space","c":[]},{"t":"Str","c":"elements"},{"t":"Space","c":[]},{"t":"Str","c":"respectively:"}]},{"t":"CodeBlock","c":[["",[],[]],"data Inline\n  = ...\n  | Span Attr [Inline]\n  | ...\n\ndata Block\n  = ...\n  | Div Attr [Block]\n  | ..."]},{"t":"Para","c":[{"t":"Str","c":"Their"},{"t":"Space","c":[]},{"t":"Str","c":"markdown"},{"t":"Space","c":[]},{"t":"Str","c":"syntax"},{"t":"Space","c":[]},{"t":"Str","c":"is"},{"t":"Space","c":[]},{"t":"Str","c":"the"},{"t":"Space","c":[]},{"t":"Str","c":"classic"},{"t":"Space","c":[]},{"t":"Str","c":"HTML"},{"t":"Space","c":[]},{"t":"Str","c":"one."}]},{"t":"Header","c":[3,["headers-get-attributes",[],[]],[{"t":"Str","c":"Headers"},{"t":"Space","c":[]},{"t":"Str","c":"get"},{"t":"Space","c":[]},{"t":"Str","c":"attributes"}]]},{"t":"Para","c":[{"t":"Str","c":"Instead"},{"t":"Space","c":[]},{"t":"Str","c":"of"}]},{"t":"CodeBlock","c":[["",[],[]],"data Block\n  = ...\n  | Header Int [Inline]\n  | ..."]},{"t":"Para","c":[{"t":"Str","c":"we"},{"t":"Space","c":[]},{"t":"Str","c":"now"},{"t":"Space","c":[]},{"t":"Str","c":"get"}]},{"t":"CodeBlock","c":[["",[],[]],"data Block\n  = ...\n  | Header Int Attr [Inline]\n  | ..."]},{"t":"Header","c":[3,["format-becomes-a-newtype",[],[]],[{"t":"Code","c":[["",[],[]],"Format"]},{"t":"Space","c":[]},{"t":"Str","c":"becomes"},{"t":"Space","c":[]},{"t":"Str","c":"a"},{"t":"Space","c":[]},{"t":"Code","c":[["",[],[]],"newtype"]}]]},{"t":"Para","c":[{"t":"Str","c":"A"},{"t":"Space","c":[]},{"t":"Str","c":"technical"},{"t":"Space","c":[]},{"t":"Str","c":"change"},{"t":"Space","c":[]},{"t":"Str","c":"to"},{"t":"Space","c":[]},{"t":"Str","c":"improve"},{"t":"Space","c":[]},{"t":"Str","c":"the"},{"t":"Space","c":[]},{"t":"Str","c":"type"},{"t":"Space","c":[]},{"t":"Str","c":"safety"},{"t":"Space","c":[]},{"t":"Str","c":"of"},{"t":"Space","c":[]},{"t":"Str","c":"the"},{"t":"Space","c":[]},{"t":"Str","c":"data"},{"t":"Space","c":[]},{"t":"Str","c":"model:"},{"t":"SoftBreak","c":[]},{"t":"Code","c":[["",[],[]],"Format"]},{"t":"Space","c":[]},{"t":"Str","c":"was"},{"t":"Space","c":[]},{"t":"Str","c":"a"},{"t":"Space","c":[]},{"t":"Str","c":"simple"},{"t":"Space","c":[]},{"t":"Str","c":"synonym"},{"t":"Space","c":[]},{"t":"Str","c":"for"},{"t":"Space","c":[]},{"t":"Code","c":[["",[],[]],"String"]}]},{"t":"CodeBlock","c":[["",[],[]],"type Format = String"]},{"t":"Para","c":[{"t":"Str","c":"It"},{"t":"Space","c":[]},{"t":"Str","c":"becomes"},{"t":"Space","c":[]},{"t":"Str","c":"a"},{"t":"Space","c":[]},{"t":"Str","c":"distinct"},{"t":"Space","c":[]},{"t":"Str","c":"type"},{"t":"Space","c":[]},{"t":"Str","c":"whose"},{"t":"Space","c":[]},{"t":"Str","c":"content"},{"t":"Space","c":[]},{"t":"Str","c":"is"},{"t":"Space","c":[]},{"t":"Str","c":"still"},{"t":"Space","c":[]},{"t":"Str","c":"a"},{"t":"Space","c":[]},{"t":"Str","c":"string:"}]},{"t":"CodeBlock","c":[["",[],[]],"newtype Format = Format String"]},{"t":"Header","c":[2,["version-1.16",[],[]],[{"t":"Str","c":"Version"},{"t":"Space","c":[]},{"t":"Str","c":"1.16"}]]},{"t":"Header","c":[3,["soft-breaks",[],[]],[{"t":"Str","c":"Soft"},{"t":"Space","c":[]},{"t":"Str","c":"breaks"}]]},{"t":"Para","c":[{"t":"Str","c":"When"},{"t":"Space","c":[]},{"t":"Str","c":"pandoc"},{"t":"Space","c":[]},{"t":"Str","c":"reads"},{"t":"Space","c":[]},{"t":"Str","c":"markdown"},{"t":"Space","c":[]},{"t":"Str","c":"files,"},{"t":"Space","c":[]},{"t":"Str","c":"only"},{"t":"Space","c":[]},{"t":"Str","c":"explicit"},{"t":"Space","c":[]},{"t":"Str","c":"line"},{"t":"Space","c":[]},{"t":"Str","c":"breaks"},{"t":"Space","c":[]},{"t":"Str","c":"–"},{"t":"SoftBreak","c":[]},{"t":"Str","c":"specified"},{"t":"Space","c":[]},{"t":"Str","c":"with"},{"t":"Space","c":[]},{"t":"Str","c":"either"},{"t":"Space","c":[]},{"t":"Code","c":[["",[],[]],"\\"]},{"t":"Space","c":[]},{"t":"Str","c":"or"},{"t":"Space","c":[]},{"t":"Str","c":"two"},{"t":"Space","c":[]},{"t":"Str","c":"spaces"},{"t":"Space","c":[]},{"t":"Str","c":"at"},{"t":"Space","c":[]},{"t":"Str","c":"the"},{"t":"Space","c":[]},{"t":"Str","c":"end"},{"t":"Space","c":[]},{"t":"Str","c":"of"},{"t":"Space","c":[]},{"t":"Str","c":"the"},{"t":"Space","c":[]},{"t":"Str","c":"line"},{"t":"Space","c":[]},{"t":"Str","c":"–"},{"t":"SoftBreak","c":[]},{"t":"Str","c":"are"},{"t":"Space","c":[]},{"t":"Str","c":"registered"},{"t":"Space","c":[]},{"t":"Str","c":"–"},{"t":"Space","c":[]},{"t":"Str","c":"as"},{"t":"Space","c":[]},{"t":"Code","c":[["",[],[]],"LineBreak"]},{"t":"Space","c":[]},{"t":"Str","c":"elements"},{"t":"Space","c":[]},{"t":"Str","c":"–"},{"t":"Space","c":[]},{"t":"Str","c":"and"},{"t":"Space","c":[]},{"t":"Str","c":"thus"},{"t":"Space","c":[]},{"t":"Str","c":"may"},{"t":"Space","c":[]},{"t":"Str","c":"be"},{"t":"SoftBreak","c":[]},{"t":"Str","c":"preserved"},{"t":"Space","c":[]},{"t":"Str","c":"in"},{"t":"Space","c":[]},{"t":"Str","c":"output"},{"t":"Space","c":[]},{"t":"Str","c":"documents."}]},{"t":"Para","c":[{"t":"Str","c":"With"},{"t":"Space","c":[]},{"t":"Str","c":"soft"},{"t":"Space","c":[]},{"t":"Str","c":"breaks,"},{"t":"Space","c":[]},{"t":"Str","c":"introduced"},{"t":"Space","c":[]},{"t":"Str","c":"in"},{"t":"Space","c":[]},{"t":"Str","c":"the"},{"t":"Space","c":[]},{"t":"Str","c":"1.16"},{"t":"Space","c":[]},{"t":"Str","c":"document"},{"t":"Space","c":[]},{"t":"Str","c":"model,"},{"t":"SoftBreak","c":[]},{"t":"Str","c":"the"},{"t":"Space","c":[]},{"t":"Str","c":"input"},{"t":"Space","c":[]},{"t":"Str","c":"to"},{"t":"Space","c":[]},{"t":"Str","c":"output"},{"t":"Space","c":[]},{"t":"Str","c":"behavior"},{"t":"Space","c":[]},{"t":"Str","c":"remains"},{"t":"Space","c":[]},{"t":"Str","c":"the"},{"t":"Space","c":[]},{"t":"Str","c":"same"},{"t":"Space","c":[]},{"t":"Str","c":"by"},{"t":"Space","c":[]},{"t":"Str","c":"default,"},{"t":"SoftBreak","c":[]},{"t":"Str","c":"but"},{"t":"Space","c":[]},{"t":"Str","c":"the"},{"t":"Space","c":[]},{"t":"Str","c":"weaker"},{"t":"Space","c":[]},{"t":"Str","c":"variants"},{"t":"Space","c":[]},{"t":"Str","c":"of"},{"t":"Space","c":[]},{"t":"Str","c":"line"},{"t":"Space","c":[]},{"t":"Str","c":"breaks,"},{"t":"Space","c":[]},{"t":"Str","c":"only"},{"t":"Space","c":[]},{"t":"Str","c":"specified"},{"t":"Space","c":[]},{"t":"Str","c":"by"},{"t":"SoftBreak","c":[]},{"t":"Str","c":"a"},{"t":"Space","c":[]},{"t":"Str","c":"new"},{"t":"Space","c":[]},{"t":"Str","c":"line"},{"t":"Space","c":[]},{"t":"Str","c":"are"},{"t":"Space","c":[]},{"t":"Str","c":"now"},{"t":"Space","c":[]},{"t":"Str","c":"registered;"},{"t":"Space","c":[]},{"t":"Str","c":"to"},{"t":"Space","c":[]},{"t":"Str","c":"make"},{"t":"Space","c":[]},{"t":"Str","c":"them"},{"t":"Space","c":[]},{"t":"Str","c":"apear"},{"t":"Space","c":[]},{"t":"Str","c":"in"},{"t":"Space","c":[]},{"t":"Str","c":"your"},{"t":"SoftBreak","c":[]},{"t":"Str","c":"output"},{"t":"Space","c":[]},{"t":"Str","c":"document,"},{"t":"Space","c":[]},{"t":"Str","c":"you"},{"t":"Space","c":[]},{"t":"Str","c":"can"},{"t":"Space","c":[]},{"t":"Str","c":"use"},{"t":"Space","c":[]},{"t":"Str","c":"the"},{"t":"Space","c":[]},{"t":"Str","c":"option"},{"t":"Space","c":[]},{"t":"Code","c":[["",[],[]],"--wrap=preserve"]},{"t":"Str","c":"."}]},{"t":"CodeBlock","c":[["",[],[]],"data Inline\n  = ...\n  | SoftBreak\n  | ..."]},{"t":"Header","c":[3,["links-and-images-get-attributes",[],[]],[{"t":"Str","c":"Links"},{"t":"Space","c":[]},{"t":"Str","c":"and"},{"t":"Space","c":[]},{"t":"Str","c":"images"},{"t":"Space","c":[]},{"t":"Str","c":"get"},{"t":"Space","c":[]},{"t":"Str","c":"attributes"}]]},{"t":"Para","c":[{"t":"Str","c":"The"},{"t":"Space","c":[]},{"t":"Str","c":"new"},{"t":"Space","c":[]},{"t":"Str","c":"model"},{"t":"Space","c":[]},{"t":"Str","c":"is:"}]},{"t":"CodeBlock","c":[["",[],[]],"data Inline\n  = ...\n  | Link Attr [Inline] Target\n  | Image Attr [Inline] Target\n  | ..."]},{"t":"Header","c":[2,["version-1.17",[],[]],[{"t":"Str","c":"Version"},{"t":"Space","c":[]},{"t":"Str","c":"1.17"}]]},{"t":"Header","c":[3,["line-blocks",[],[]],[{"t":"Str","c":"Line"},{"t":"Space","c":[]},{"t":"Str","c":"blocks"}]]},{"t":"Para","c":[{"t":"Str","c":"A"},{"t":"Space","c":[]},{"t":"Str","c":"structure"},{"t":"Space","c":[]},{"t":"Str","c":"that"},{"t":"Space","c":[]},{"t":"Str","c":"preserves"},{"t":"Space","c":[]},{"t":"Str","c":"line"},{"t":"Space","c":[]},{"t":"Str","c":"breaks"},{"t":"Space","c":[]},{"t":"Str","c":"and"},{"t":"Space","c":[]},{"t":"Str","c":"leading"},{"t":"Space","c":[]},{"t":"Str","c":"spaces"},{"t":"SoftBreak","c":[]},{"t":"Str","c":"(refer"},{"t":"Space","c":[]},{"t":"Str","c":"to"},{"t":"Space","c":[]},{"t":"Str","c":"the"},{"t":"Space","c":[]},{"t":"Link","c":[["",[],[]],[{"t":"Str","c":"user"},{"t":"Space","c":[]},{"t":"Str","c":"manual"}],["https://pandoc.org/MANUAL.html#line-blocks",""]]},{"t":"Space","c":[]},{"t":"Str","c":"for"},{"t":"Space","c":[]},{"t":"Str","c":"details):"}]},{"t":"CodeBlock","c":[["",[],[]],"data Block\n  = ...\n  | LineBlock [[Inline]]\n  | ..."]},{"t":"Header","c":[2,["version-1.19",[],[]],[{"t":"Str","c":"Version"},{"t":"Space","c":[]},{"t":"Str","c":"1.19"}]]},{"t":"Para","c":[{"t":"Str","c":"No"},{"t":"Space","c":[]},{"t":"Str","c":"change"},{"t":"Space","c":[]},{"t":"Str","c":"with"},{"t":"Space","c":[]},{"t":"Str","c":"respect"},{"t":"Space","c":[]},{"t":"Str","c":"to"},{"t":"Space","c":[]},{"t":"Str","c":"1.17."}]},{"t":"Header","c":[2,["version-2.0",[],[]],[{"t":"Str","c":"Version"},{"t":"Space","c":[]},{"t":"Str","c":"2.0"}]]},{"t":"Para","c":[{"t":"Str","c":"No"},{"t":"Space","c":[]},{"t":"Str","c":"change"},{"t":"Space","c":[]},{"t":"Str","c":"with"},{"t":"Space","c":[]},{"t":"Str","c":"respect"},{"t":"Space","c":[]},{"t":"Str","c":"to"},{"t":"Space","c":[]},{"t":"Str","c":"1.19."}]},{"t":"Header","c":[2,["version-2.1",[],[]],[{"t":"Str","c":"Version"},{"t":"Space","c":[]},{"t":"Str","c":"2.1"}]]},{"t":"Para","c":[{"t":"Str","c":"No"},{"t":"Space","c":[]},{"t":"Str","c":"change"},{"t":"Space","c":[]},{"t":"Str","c":"with"},{"t":"Space","c":[]},{"t":"Str","c":"respect"},{"t":"Space","c":[]},{"t":"Str","c":"to"},{"t":"Space","c":[]},{"t":"Str","c":"2.0."}]}]]
